epkernel/Analysis.py
epkernel/Application.py
epkernel/BASE.py
epkernel/Configuration.py
epkernel/GUI.py
epkernel/Guide.py
epkernel/Input.py
epkernel/Optimization.py
epkernel/Output.py
epkernel/__init__.py
epkernel/epcam.py
epkernel/Action/Information.py
epkernel/Action/Selection.py
epkernel/Edition/Job.py
epkernel/Edition/Layers.py
epkernel/Edition/Matrix.py
epkernel/MI/stackup.py
epkernel-1.1.9.dist-info/METADATA
epkernel-1.1.9.dist-info/WHEEL
epkernel-1.1.9.dist-info/top_level.txt
epkernel-1.1.9.dist-info/RECORD
