Metadata-Version: 2.1
Name: epkernel
Version: 1.1.9
Summary: epcam api
Home-page: UNKNOWN
Author: panfeng
Author-email: panfeng2903@163.com
License: MIT Licence
Platform: UNKNOWN
Requires-Python: >=3.7.0
Requires-Dist: requests
